postgreconnection/__init__.py
postgreconnection/databaseop.py
my_database_package-0.1.dist-info/METADATA
my_database_package-0.1.dist-info/WHEEL
my_database_package-0.1.dist-info/top_level.txt
my_database_package-0.1.dist-info/RECORD
